inference/__init__.py
inference/openai/__init__.py
inference/openai/openai_client.py
inference/util/__init__.py
inference/util/base64.py
inference_python_sdk-0.1.6.dist-info/METADATA
inference_python_sdk-0.1.6.dist-info/WHEEL
inference_python_sdk-0.1.6.dist-info/top_level.txt
inference_python_sdk-0.1.6.dist-info/RECORD
