Metadata-Version: 2.4
Name: inference-python-sdk
Version: 0.1.6
Requires-Python: >=3.7
Requires-Dist: httpx
Requires-Dist: openai
Requires-Dist: pyrate_limiter==2.7.0
Requires-Dist: tenacity
Requires-Dist: pyyaml
Dynamic: requires-dist
Dynamic: requires-python
